tests/test_wunderpython.py
tests/__init__.py
wunderpython/stupidcache.py
wunderpython/wunderground.py
wunderpython/__init__.py
WunderPython-0.1a1.dist-info/metadata.json
WunderPython-0.1a1.dist-info/WHEEL
WunderPython-0.1a1.dist-info/RECORD
WunderPython-0.1a1.dist-info/DESCRIPTION.rst
WunderPython-0.1a1.dist-info/top_level.txt
WunderPython-0.1a1.dist-info/METADATA
