Metadata-Version: 2.0
Name: WunderPython
Version: 0.1a1
Summary: API wrapper for the Wunderground API
Home-page: https://github.com/RobinJespersen/WunderPython
Author: Robin Jespersen
Author-email: robin.jespersen@tum.de
License: MIT
Keywords: weather data wunderground
Platform: UNKNOWN
Classifier: Development Status :: 3 - Alpha
Classifier: Intended Audience :: Science/Research
Classifier: Intended Audience :: Developers
Classifier: Intended Audience :: Education
Classifier: License :: OSI Approved :: MIT License
Classifier: Programming Language :: Python :: 2
Classifier: Programming Language :: Python :: 2.7
